topsis_pkg.py
topsis_yashika_102317089-1.0.1.dist-info/METADATA
topsis_yashika_102317089-1.0.1.dist-info/WHEEL
topsis_yashika_102317089-1.0.1.dist-info/entry_points.txt
topsis_yashika_102317089-1.0.1.dist-info/top_level.txt
topsis_yashika_102317089-1.0.1.dist-info/RECORD
