Metadata-Version: 2.4
Name: Topsis-Yashika-102317089
Version: 1.0.1
Requires-Dist: pandas
Requires-Dist: numpy
Dynamic: description
Dynamic: description-content-type
Dynamic: requires-dist
